[
    {
        "ShipName": "ShipName1",
        "ShipAddress": "ShipAddress1",
        "ShipCity": "ShipCity1",
        "ShipRegion": "ShipRegion1",
        "ShipPostalCode": "ShipPosta1",
        "ShipCountry": "ShipCountry1",
        "CustomerID": "Cust1",
        "CustomerName": "NJyLZpFfTwcTByOCByjFojMgMWznSTsA",
        "Address": "Address1",
        "City": "City1",
        "Region": "Region1",
        "PostalCode": "PostalCod1",
        "Country": "Country1",
        "Salesperson": "nQSGQIscnXYunsqXqmAZvmFUoKpjeOc",
        "OrderID": 1341540969,
        "OrderDate": "/Date(854856195000)/",
        "RequiredDate": "/Date(794266015000)/",
        "ShippedDate": "/Date(1157949037000)/",
        "ShipperName": "wegIJzWIAnsdJKOcGvOdRMWPfBWjCYaQ",
        "ProductID": 1110758537,
        "ProductName": "bIcjnUEshdNLpSWbYDAYrXCSdQWoMXqJ",
        "UnitPrice": 12448813579.9765,
        "Quantity": 9643,
        "Discount": 81.833,
        "ExtendedPrice": 98368232953.3621,
        "Freight": 70850239275.0233
    },
    {
        "ShipName": "ShipName2",
        "ShipAddress": "ShipAddress2",
        "ShipCity": "ShipCity2",
        "ShipRegion": "ShipRegion2",
        "ShipPostalCode": "ShipPosta2",
        "ShipCountry": "ShipCountry2",
        "CustomerID": "Cust2",
        "CustomerName": "xlvlxqEDYMMDBDwBfKdneoMGVhYKYeBt",
        "Address": "Address2",
        "City": "City2",
        "Region": "Region2",
        "PostalCode": "PostalCod2",
        "Country": "Country2",
        "Salesperson": "XifXHxoZWIFJUXqaVDslikxyTnoCKSc",
        "OrderID": 1613014057,
        "OrderDate": "/Date(1355466857000)/",
        "RequiredDate": "/Date(480008917000)/",
        "ShippedDate": "/Date(1342648102000)/",
        "ShipperName": "KfiEaxAqnBMqYddiWUECzunfwmgeqDsR",
        "ProductID": 1966254736,
        "ProductName": "UEprAvzgOQSTsRXzvlZZGoyQlZtafRlR",
        "UnitPrice": 95211735670.4547,
        "Quantity": 2916,
        "Discount": 13.716,
        "ExtendedPrice": 67672696756.199,
        "Freight": 50902720610.6111
    },
    {
        "ShipName": "ShipName3",
        "ShipAddress": "ShipAddress3",
        "ShipCity": "ShipCity3",
        "ShipRegion": "ShipRegion3",
        "ShipPostalCode": "ShipPosta3",
        "ShipCountry": "ShipCountry3",
        "CustomerID": "Cust3",
        "CustomerName": "ZMehTbBLKDVbmInIaVGquSrjaCkPVLVF",
        "Address": "Address3",
        "City": "City3",
        "Region": "Region3",
        "PostalCode": "PostalCod3",
        "Country": "Country3",
        "Salesperson": "EoGhxtSzBCZFOSwFAATBfOgHnmxfbbu",
        "OrderID": 866353267,
        "OrderDate": "/Date(1267854369000)/",
        "RequiredDate": "/Date(815870009000)/",
        "ShippedDate": "/Date(1324525110000)/",
        "ShipperName": "yFAIcUfBQNRwzqlGMGntQStHJFMgrHwj",
        "ProductID": 175682125,
        "ProductName": "rUyVwNfRhQCBXlTcjRcLnUzXcHxUymyd",
        "UnitPrice": 15062834625.1323,
        "Quantity": 29011,
        "Discount": 34.377,
        "ExtendedPrice": 25004278076.8126,
        "Freight": 1600982830.8597
    },
    {
        "ShipName": "ShipName4",
        "ShipAddress": "ShipAddress4",
        "ShipCity": "ShipCity4",
        "ShipRegion": "ShipRegion4",
        "ShipPostalCode": "ShipPosta4",
        "ShipCountry": "ShipCountry4",
        "CustomerID": "Cust4",
        "CustomerName": "mXrqaSWgjbbYijtzYJIAOvRqLUziEEaa",
        "Address": "Address4",
        "City": "City4",
        "Region": "Region4",
        "PostalCode": "PostalCod4",
        "Country": "Country4",
        "Salesperson": "skgQVbMNNEsgrKFQSrshGJJzbBPIdSk",
        "OrderID": 104521087,
        "OrderDate": "/Date(45375407000)/",
        "RequiredDate": "/Date(684567034000)/",
        "ShippedDate": "/Date(989159967000)/",
        "ShipperName": "BvSnVdMGGnBrWXzxEBJdiQtEuiuLcoBe",
        "ProductID": 1792384466,
        "ProductName": "BTCzYctMZGCgnbxCJrsHvFcBhcSkfzqA",
        "UnitPrice": 10769597766.9209,
        "Quantity": 20863,
        "Discount": 27.056,
        "ExtendedPrice": 43901948281.5638,
        "Freight": 78651765850.3726
    },
    {
        "ShipName": "ShipName5",
        "ShipAddress": "ShipAddress5",
        "ShipCity": "ShipCity5",
        "ShipRegion": "ShipRegion5",
        "ShipPostalCode": "ShipPosta5",
        "ShipCountry": "ShipCountry5",
        "CustomerID": "Cust5",
        "CustomerName": "QSssYbgxXLlxHbLkUHXESUHWNhdiqADJ",
        "Address": "Address5",
        "City": "City5",
        "Region": "Region5",
        "PostalCode": "PostalCod5",
        "Country": "Country5",
        "Salesperson": "BiZsLYANGSPLSTNKXXUxwvKYJgBHPfU",
        "OrderID": 658651598,
        "OrderDate": "/Date(64547078000)/",
        "RequiredDate": "/Date(562029098000)/",
        "ShippedDate": "/Date(302155041000)/",
        "ShipperName": "LWAvoQUPQZnfoOapfAMnkPvOhXOKBLfX",
        "ProductID": 800940504,
        "ProductName": "blZVhEqJXKznUkmTpdnYfioxiFiRTpwH",
        "UnitPrice": 37946591456.4207,
        "Quantity": 9794,
        "Discount": 97.08,
        "ExtendedPrice": 524214468.8963,
        "Freight": 45665065315.552
    },
    {
        "ShipName": "ShipName6",
        "ShipAddress": "ShipAddress6",
        "ShipCity": "ShipCity6",
        "ShipRegion": "ShipRegion6",
        "ShipPostalCode": "ShipPosta6",
        "ShipCountry": "ShipCountry6",
        "CustomerID": "Cust6",
        "CustomerName": "vwdgmJPaJHLzQLalAEOeyDENEyHjJYDv",
        "Address": "Address6",
        "City": "City6",
        "Region": "Region6",
        "PostalCode": "PostalCod6",
        "Country": "Country6",
        "Salesperson": "kxQbdqFTckFbgvvdsDCZUlOYzWHMSGe",
        "OrderID": 549672676,
        "OrderDate": "/Date(1118324186000)/",
        "RequiredDate": "/Date(1227829999000)/",
        "ShippedDate": "/Date(168542600000)/",
        "ShipperName": "oDwtuuVijFTRORPcSVKCPnGOxdvdicPl",
        "ProductID": 1639652610,
        "ProductName": "CuhnjkLXhWhuGkvjyhjCsvJZoETbRSRg",
        "UnitPrice": 77948948834.0914,
        "Quantity": 18379,
        "Discount": 95.844,
        "ExtendedPrice": 49760524346.4931,
        "Freight": 18050352786.6676
    },
    {
        "ShipName": "ShipName7",
        "ShipAddress": "ShipAddress7",
        "ShipCity": "ShipCity7",
        "ShipRegion": "ShipRegion7",
        "ShipPostalCode": "ShipPosta7",
        "ShipCountry": "ShipCountry7",
        "CustomerID": "Cust7",
        "CustomerName": "vKzekZPxuesCYbsYgKoyzUYYwGKRplBq",
        "Address": "Address7",
        "City": "City7",
        "Region": "Region7",
        "PostalCode": "PostalCod7",
        "Country": "Country7",
        "Salesperson": "XDCVaiqyqtgbSLPelyQuFyxJbNjMJpx",
        "OrderID": 1610728587,
        "OrderDate": "/Date(126899013000)/",
        "RequiredDate": "/Date(1404088495000)/",
        "ShippedDate": "/Date(1338598852000)/",
        "ShipperName": "fOVSIHfJNphONXQVIjuFfbISjtQfjVaA",
        "ProductID": 1460437086,
        "ProductName": "hdAraDXehsuTDTlVRxGCPqArCUagFjvB",
        "UnitPrice": 1425708387.9783,
        "Quantity": 18587,
        "Discount": 67.585,
        "ExtendedPrice": 9099785750.7318,
        "Freight": 50556815671.7345
    },
    {
        "ShipName": "ShipName8",
        "ShipAddress": "ShipAddress8",
        "ShipCity": "ShipCity8",
        "ShipRegion": "ShipRegion8",
        "ShipPostalCode": "ShipPosta8",
        "ShipCountry": "ShipCountry8",
        "CustomerID": "Cust8",
        "CustomerName": "cjenfOCiPyoyWGinZQyPJxcPQKfByWYA",
        "Address": "Address8",
        "City": "City8",
        "Region": "Region8",
        "PostalCode": "PostalCod8",
        "Country": "Country8",
        "Salesperson": "uzGNufvrZepGlQxTaCKSreqWEMvvGGj",
        "OrderID": 1793301046,
        "OrderDate": "/Date(571006866000)/",
        "RequiredDate": "/Date(958046476000)/",
        "ShippedDate": "/Date(1450227814000)/",
        "ShipperName": "phUQpmsfwlCFrlSveXSvjzZbpxBeThKM",
        "ProductID": 2002651,
        "ProductName": "EIkjwSUaLryYEbLmTMJmHpUlrxxSPDyo",
        "UnitPrice": 78297573095.1875,
        "Quantity": 32704,
        "Discount": 28.276,
        "ExtendedPrice": 86279703490.436,
        "Freight": 5752831441.3502
    },
    {
        "ShipName": "ShipName9",
        "ShipAddress": "ShipAddress9",
        "ShipCity": "ShipCity9",
        "ShipRegion": "ShipRegion9",
        "ShipPostalCode": "ShipPosta9",
        "ShipCountry": "ShipCountry9",
        "CustomerID": "Cust9",
        "CustomerName": "mgEIjoJdHHtltseEUxQMbXRGhcvfwpnh",
        "Address": "Address9",
        "City": "City9",
        "Region": "Region9",
        "PostalCode": "PostalCod9",
        "Country": "Country9",
        "Salesperson": "DIFMhsXFhyvSkPYIBdSCfXgWduttbxK",
        "OrderID": 295054312,
        "OrderDate": "/Date(786092782000)/",
        "RequiredDate": "/Date(1374287382000)/",
        "ShippedDate": "/Date(878856988000)/",
        "ShipperName": "dFPXmhzsJeiPZoCUkXIFiyOOQFWVRotk",
        "ProductID": 114970916,
        "ProductName": "kRcuQsTKCklMyoXulcaIgJrNzJuJGqHu",
        "UnitPrice": 12270642956.7188,
        "Quantity": 13507,
        "Discount": 0.982,
        "ExtendedPrice": 94406733452.3424,
        "Freight": 14285308448.5977
    },
    {
        "ShipName": "ShipName10",
        "ShipAddress": "ShipAddress10",
        "ShipCity": "ShipCity10",
        "ShipRegion": "ShipRegion10",
        "ShipPostalCode": "ShipPost10",
        "ShipCountry": "ShipCountry10",
        "CustomerID": "Cus10",
        "CustomerName": "FSIymiMXwTDaeXPhmfUoFKqNaXWojGKn",
        "Address": "Address10",
        "City": "City10",
        "Region": "Region10",
        "PostalCode": "PostalCo10",
        "Country": "Country10",
        "Salesperson": "cWWnzJhazxLbTgJPujrdojFgoQOQuir",
        "OrderID": 1219573074,
        "OrderDate": "/Date(712394439000)/",
        "RequiredDate": "/Date(690404792000)/",
        "ShippedDate": "/Date(961646968000)/",
        "ShipperName": "hWkXXxGmbvKohTyEvatpAfMLFbIjebIm",
        "ProductID": 1233858729,
        "ProductName": "flQHAgcQUGYGcvTHFKPpQlLKRVfFRIlE",
        "UnitPrice": 8030910883.0988,
        "Quantity": 8209,
        "Discount": 8.082,
        "ExtendedPrice": 81727429619.0589,
        "Freight": 52888099476.695
    },
    {
        "ShipName": "ShipName11",
        "ShipAddress": "ShipAddress11",
        "ShipCity": "ShipCity11",
        "ShipRegion": "ShipRegion11",
        "ShipPostalCode": "ShipPost11",
        "ShipCountry": "ShipCountry11",
        "CustomerID": "Cus11",
        "CustomerName": "BuqflPOkNtKSthvyBBlAptyXtEhcNPZH",
        "Address": "Address11",
        "City": "City11",
        "Region": "Region11",
        "PostalCode": "PostalCo11",
        "Country": "Country11",
        "Salesperson": "stJyAntvoXVvCEvWvHWeAUPORgOOHxl",
        "OrderID": 475217450,
        "OrderDate": "/Date(544578306000)/",
        "RequiredDate": "/Date(885403118000)/",
        "ShippedDate": "/Date(848438553000)/",
        "ShipperName": "APCVYSgiCoizTiSteSnIXqNGZWakHwVa",
        "ProductID": 1769698203,
        "ProductName": "uavttqgydkrqPrOhgWjSqJbWCDNoRJlZ",
        "UnitPrice": 10057626292.1094,
        "Quantity": 15897,
        "Discount": 5.277,
        "ExtendedPrice": 81745389802.3813,
        "Freight": 55588253145.1061
    },
    {
        "ShipName": "ShipName12",
        "ShipAddress": "ShipAddress12",
        "ShipCity": "ShipCity12",
        "ShipRegion": "ShipRegion12",
        "ShipPostalCode": "ShipPost12",
        "ShipCountry": "ShipCountry12",
        "CustomerID": "Cus12",
        "CustomerName": "yediCSykOuYkiEHUJopWYwwmYnvZXzIA",
        "Address": "Address12",
        "City": "City12",
        "Region": "Region12",
        "PostalCode": "PostalCo12",
        "Country": "Country12",
        "Salesperson": "tVBhTUahSARQSMwddHJMyyleLrDFOeF",
        "OrderID": 2118752285,
        "OrderDate": "/Date(509460795000)/",
        "RequiredDate": "/Date(588826292000)/",
        "ShippedDate": "/Date(237978475000)/",
        "ShipperName": "YClAIdntRKXEeErSNJKPVnsgBfFfBbHe",
        "ProductID": 1668907084,
        "ProductName": "JBwPynQKPFyfrKNSbXnzEItDlIvHwtNQ",
        "UnitPrice": 46742820180.9525,
        "Quantity": 23462,
        "Discount": 92.103,
        "ExtendedPrice": 78739571338.5194,
        "Freight": 56650748220.2723
    },
    {
        "ShipName": "ShipName13",
        "ShipAddress": "ShipAddress13",
        "ShipCity": "ShipCity13",
        "ShipRegion": "ShipRegion13",
        "ShipPostalCode": "ShipPost13",
        "ShipCountry": "ShipCountry13",
        "CustomerID": "Cus13",
        "CustomerName": "JiFbjXGgyGoNXONdwrWXxFueEiKqKeOw",
        "Address": "Address13",
        "City": "City13",
        "Region": "Region13",
        "PostalCode": "PostalCo13",
        "Country": "Country13",
        "Salesperson": "NvTAlYaGlEcLYtAfyDxKSEyqLvkJlaw",
        "OrderID": 1831304683,
        "OrderDate": "/Date(894109456000)/",
        "RequiredDate": "/Date(1130088283000)/",
        "ShippedDate": "/Date(1455342252000)/",
        "ShipperName": "LapBEdFmDtwrKaYMyWSQqXeMmMiuTHsZ",
        "ProductID": 197753637,
        "ProductName": "WZNqNEnRppxsbEeHHhnYstthWXmhBKFe",
        "UnitPrice": 33055862132.4598,
        "Quantity": 20186,
        "Discount": 88.364,
        "ExtendedPrice": 62470541498.6237,
        "Freight": 7006150064.9899
    },
    {
        "ShipName": "ShipName14",
        "ShipAddress": "ShipAddress14",
        "ShipCity": "ShipCity14",
        "ShipRegion": "ShipRegion14",
        "ShipPostalCode": "ShipPost14",
        "ShipCountry": "ShipCountry14",
        "CustomerID": "Cus14",
        "CustomerName": "qocJKZrunInhZsQFsLfBZWkOctkzApML",
        "Address": "Address14",
        "City": "City14",
        "Region": "Region14",
        "PostalCode": "PostalCo14",
        "Country": "Country14",
        "Salesperson": "hCTSArgemZxOtCiVhjBVOoAmRrzfgyw",
        "OrderID": 348324735,
        "OrderDate": "/Date(1205793621000)/",
        "RequiredDate": "/Date(239287374000)/",
        "ShippedDate": "/Date(22964134000)/",
        "ShipperName": "TJTJdQuFfrCrknGaNtqIonCFRkfnHKvc",
        "ProductID": 581579142,
        "ProductName": "EozemTYMpceplACZJTiUjlBJVsGFKOXL",
        "UnitPrice": 39023969252.5938,
        "Quantity": 14808,
        "Discount": 7.913,
        "ExtendedPrice": 81180053763.0915,
        "Freight": 51073911576.5318
    },
    {
        "ShipName": "ShipName15",
        "ShipAddress": "ShipAddress15",
        "ShipCity": "ShipCity15",
        "ShipRegion": "ShipRegion15",
        "ShipPostalCode": "ShipPost15",
        "ShipCountry": "ShipCountry15",
        "CustomerID": "Cus15",
        "CustomerName": "tzIKrugHtppxckcUEWJCnlkJfeKeWChu",
        "Address": "Address15",
        "City": "City15",
        "Region": "Region15",
        "PostalCode": "PostalCo15",
        "Country": "Country15",
        "Salesperson": "wKedtoyxghiSWJbkgiiHTuoydgHdMFP",
        "OrderID": 1999736289,
        "OrderDate": "/Date(497147977000)/",
        "RequiredDate": "/Date(441526171000)/",
        "ShippedDate": "/Date(908086880000)/",
        "ShipperName": "HPYNVmZjhVlMoCiIEcYFwWYCGIXhYqfq",
        "ProductID": 509096572,
        "ProductName": "oWjHPnWIgVRPLuzlNvWrFdSHDMLvcxGL",
        "UnitPrice": 60691545507.8706,
        "Quantity": 21575,
        "Discount": 85.211,
        "ExtendedPrice": 47972127841.7855,
        "Freight": 30188087746.5009
    },
    {
        "ShipName": "ShipName16",
        "ShipAddress": "ShipAddress16",
        "ShipCity": "ShipCity16",
        "ShipRegion": "ShipRegion16",
        "ShipPostalCode": "ShipPost16",
        "ShipCountry": "ShipCountry16",
        "CustomerID": "Cus16",
        "CustomerName": "hdxDzmbdQzVdhowBofTtAEFxXUruToHA",
        "Address": "Address16",
        "City": "City16",
        "Region": "Region16",
        "PostalCode": "PostalCo16",
        "Country": "Country16",
        "Salesperson": "kCWPkdVmuXFfvbcmSCooPJIgZuwUfHT",
        "OrderID": 1325796793,
        "OrderDate": "/Date(73931783000)/",
        "RequiredDate": "/Date(1117427647000)/",
        "ShippedDate": "/Date(792757373000)/",
        "ShipperName": "MXOZISifFBJGNuuGbSSSXHLDNgUUcEui",
        "ProductID": 795486389,
        "ProductName": "pxUwBaLBZJTCSZSzWbardwYFJTjGWuwo",
        "UnitPrice": 24268025904.8938,
        "Quantity": 13937,
        "Discount": 28.859,
        "ExtendedPrice": 40720059094.0192,
        "Freight": 38416570099.0706
    },
    {
        "ShipName": "ShipName17",
        "ShipAddress": "ShipAddress17",
        "ShipCity": "ShipCity17",
        "ShipRegion": "ShipRegion17",
        "ShipPostalCode": "ShipPost17",
        "ShipCountry": "ShipCountry17",
        "CustomerID": "Cus17",
        "CustomerName": "faPIqnVMyVAyklFfAjKurxilhwxbIZFp",
        "Address": "Address17",
        "City": "City17",
        "Region": "Region17",
        "PostalCode": "PostalCo17",
        "Country": "Country17",
        "Salesperson": "sbWGxcSZHtWIvMWKNlGJUCsHvHqQRAD",
        "OrderID": 1097753594,
        "OrderDate": "/Date(859419232000)/",
        "RequiredDate": "/Date(821793219000)/",
        "ShippedDate": "/Date(259664471000)/",
        "ShipperName": "tusgrUoWeBlUkAPJACXlAAOOjVCJAgPi",
        "ProductID": 142106881,
        "ProductName": "UXrfBswvFIbRxRpCqKdHkdinqZSUtnQT",
        "UnitPrice": 71128498273.9016,
        "Quantity": 31617,
        "Discount": 46.717,
        "ExtendedPrice": 73530212230.9803,
        "Freight": 28035983792.5061
    },
    {
        "ShipName": "ShipName18",
        "ShipAddress": "ShipAddress18",
        "ShipCity": "ShipCity18",
        "ShipRegion": "ShipRegion18",
        "ShipPostalCode": "ShipPost18",
        "ShipCountry": "ShipCountry18",
        "CustomerID": "Cus18",
        "CustomerName": "dVPbfAyGPPUuhmIbtTzsCcbKkTfDImdB",
        "Address": "Address18",
        "City": "City18",
        "Region": "Region18",
        "PostalCode": "PostalCo18",
        "Country": "Country18",
        "Salesperson": "AknVQkhfsnIfqeHKQTPGKJDEsqsAcRQ",
        "OrderID": 512209226,
        "OrderDate": "/Date(847796662000)/",
        "RequiredDate": "/Date(891471186000)/",
        "ShippedDate": "/Date(131709968000)/",
        "ShipperName": "GCipUCeWrzWAeYSSTOYvpzwiDvCEDMmy",
        "ProductID": 424541123,
        "ProductName": "OdXLEvVdyRWuQaIWQnISxWySnnoCmewu",
        "UnitPrice": 63073481922.0378,
        "Quantity": 18015,
        "Discount": 22.303,
        "ExtendedPrice": 52784039569.0873,
        "Freight": 35668192640.8782
    },
    {
        "ShipName": "ShipName19",
        "ShipAddress": "ShipAddress19",
        "ShipCity": "ShipCity19",
        "ShipRegion": "ShipRegion19",
        "ShipPostalCode": "ShipPost19",
        "ShipCountry": "ShipCountry19",
        "CustomerID": "Cus19",
        "CustomerName": "ZoqckAVwkHiClRoEClPlTYcwXUHKmqdr",
        "Address": "Address19",
        "City": "City19",
        "Region": "Region19",
        "PostalCode": "PostalCo19",
        "Country": "Country19",
        "Salesperson": "UNuBtAyXmclzljTwuAqfhXpyjVPHfUs",
        "OrderID": 1693960764,
        "OrderDate": "/Date(1340345369000)/",
        "RequiredDate": "/Date(932967665000)/",
        "ShippedDate": "/Date(636083219000)/",
        "ShipperName": "kgtDaJpRpCgDSZBxTKeztLvpnAbhbdGG",
        "ProductID": 1972383602,
        "ProductName": "honLvPjxSfHNyDFzunbprAxQqSUbtxxH",
        "UnitPrice": 3901872457.9364,
        "Quantity": 31708,
        "Discount": 79.665,
        "ExtendedPrice": 19044797471.7244,
        "Freight": 96531148790.3818
    },
    {
        "ShipName": "ShipName20",
        "ShipAddress": "ShipAddress20",
        "ShipCity": "ShipCity20",
        "ShipRegion": "ShipRegion20",
        "ShipPostalCode": "ShipPost20",
        "ShipCountry": "ShipCountry20",
        "CustomerID": "Cus20",
        "CustomerName": "PEaoyXBjxIBumXperejHMMLscCHJrVKt",
        "Address": "Address20",
        "City": "City20",
        "Region": "Region20",
        "PostalCode": "PostalCo20",
        "Country": "Country20",
        "Salesperson": "nypdJuhvyUWvpFeVRbMvBzDrUgdVLDq",
        "OrderID": 455511746,
        "OrderDate": "/Date(771365373000)/",
        "RequiredDate": "/Date(491003513000)/",
        "ShippedDate": "/Date(927419564000)/",
        "ShipperName": "vnxGTRzKFYstMcKuSBCtWvyWavJwDODo",
        "ProductID": 809863905,
        "ProductName": "cCuNJKIaoDimURgmqidvQNWvQbbjqpkp",
        "UnitPrice": 69357531191.7811,
        "Quantity": 15537,
        "Discount": 63.244,
        "ExtendedPrice": 46797589515.3358,
        "Freight": 60398161411.2853
    },
    {
        "ShipName": "ShipName21",
        "ShipAddress": "ShipAddress21",
        "ShipCity": "ShipCity21",
        "ShipRegion": "ShipRegion21",
        "ShipPostalCode": "ShipPost21",
        "ShipCountry": "ShipCountry21",
        "CustomerID": "Cus21",
        "CustomerName": "AyFHHPxvfCcNBNCzdghVWhraZCxEPgiX",
        "Address": "Address21",
        "City": "City21",
        "Region": "Region21",
        "PostalCode": "PostalCo21",
        "Country": "Country21",
        "Salesperson": "cveFLkDUXztSEHvZbTeTNvEMPjafEdX",
        "OrderID": 550454654,
        "OrderDate": "/Date(171750103000)/",
        "RequiredDate": "/Date(868872428000)/",
        "ShippedDate": "/Date(571969124000)/",
        "ShipperName": "CTjxgVqWnNWNAnmHSjMXWgUXHmIWNznQ",
        "ProductID": 1240820178,
        "ProductName": "auneOLoucWqlWjAaONpNiXymbiENnyPE",
        "UnitPrice": 33682734472.6771,
        "Quantity": 2966,
        "Discount": 4.739,
        "ExtendedPrice": 19479397963.7324,
        "Freight": 19148010108.6199
    },
    {
        "ShipName": "ShipName22",
        "ShipAddress": "ShipAddress22",
        "ShipCity": "ShipCity22",
        "ShipRegion": "ShipRegion22",
        "ShipPostalCode": "ShipPost22",
        "ShipCountry": "ShipCountry22",
        "CustomerID": "Cus22",
        "CustomerName": "aYmLyhsbPsTxPJxIBSFfVWQRusdOQlaJ",
        "Address": "Address22",
        "City": "City22",
        "Region": "Region22",
        "PostalCode": "PostalCo22",
        "Country": "Country22",
        "Salesperson": "XBGkfYhWAxOAAQkZAKnBoONkgNrqpHM",
        "OrderID": 517922304,
        "OrderDate": "/Date(663175693000)/",
        "RequiredDate": "/Date(732855117000)/",
        "ShippedDate": "/Date(131227974000)/",
        "ShipperName": "RvfAbvbhTHxWPUFExYsBeLpxKolxZVTd",
        "ProductID": 1691614061,
        "ProductName": "TKbCblBnjGUPyvfZNbcaSNSFSdWUYZvr",
        "UnitPrice": 61962995934.3001,
        "Quantity": 17438,
        "Discount": 60.616,
        "ExtendedPrice": 79479261627.4207,
        "Freight": 8552614878.863
    },
    {
        "ShipName": "ShipName23",
        "ShipAddress": "ShipAddress23",
        "ShipCity": "ShipCity23",
        "ShipRegion": "ShipRegion23",
        "ShipPostalCode": "ShipPost23",
        "ShipCountry": "ShipCountry23",
        "CustomerID": "Cus23",
        "CustomerName": "TalhJvpzrthcSFJrhWvsDBCEMufHhVYm",
        "Address": "Address23",
        "City": "City23",
        "Region": "Region23",
        "PostalCode": "PostalCo23",
        "Country": "Country23",
        "Salesperson": "CZqFCJTjSQEvdfpPsVVzjndufwzLKKU",
        "OrderID": 1383421292,
        "OrderDate": "/Date(640208418000)/",
        "RequiredDate": "/Date(366550682000)/",
        "ShippedDate": "/Date(1410265598000)/",
        "ShipperName": "gHBJHYXlWExMvyDfaBcsEirOctoMYWHr",
        "ProductID": 1675809158,
        "ProductName": "XBeBVypYohRClzjGAOoMojdhQPnVCNeh",
        "UnitPrice": 1093476521.7825,
        "Quantity": 14361,
        "Discount": 35.897,
        "ExtendedPrice": 76986518874.7644,
        "Freight": 85426165722.3105
    },
    {
        "ShipName": "ShipName24",
        "ShipAddress": "ShipAddress24",
        "ShipCity": "ShipCity24",
        "ShipRegion": "ShipRegion24",
        "ShipPostalCode": "ShipPost24",
        "ShipCountry": "ShipCountry24",
        "CustomerID": "Cus24",
        "CustomerName": "PJEipEjXutuCsSSFemLUnZNLjLmueDGy",
        "Address": "Address24",
        "City": "City24",
        "Region": "Region24",
        "PostalCode": "PostalCo24",
        "Country": "Country24",
        "Salesperson": "ZmJGXpivjazRsRkwucdMdiUtxPxxIPR",
        "OrderID": 846847465,
        "OrderDate": "/Date(441149316000)/",
        "RequiredDate": "/Date(1456259679000)/",
        "ShippedDate": "/Date(788582487000)/",
        "ShipperName": "FFISJhqDSCrdHWvsbGpZVBpGbhgBfDvo",
        "ProductID": 565278448,
        "ProductName": "ttSZseLULJgztZEtDhIqOnIPkmYUWrRA",
        "UnitPrice": 41389614040.9633,
        "Quantity": 15975,
        "Discount": 63.758,
        "ExtendedPrice": 36354019399.7323,
        "Freight": 69575218087.9935
    },
    {
        "ShipName": "ShipName25",
        "ShipAddress": "ShipAddress25",
        "ShipCity": "ShipCity25",
        "ShipRegion": "ShipRegion25",
        "ShipPostalCode": "ShipPost25",
        "ShipCountry": "ShipCountry25",
        "CustomerID": "Cus25",
        "CustomerName": "akChpCNLSJcUaHNsEkteFMOWvAyvWOIe",
        "Address": "Address25",
        "City": "City25",
        "Region": "Region25",
        "PostalCode": "PostalCo25",
        "Country": "Country25",
        "Salesperson": "dyAxGbIgODPKNPGJWsnTsFOGWNZUDNi",
        "OrderID": 2040328677,
        "OrderDate": "/Date(619368943000)/",
        "RequiredDate": "/Date(264301759000)/",
        "ShippedDate": "/Date(674239266000)/",
        "ShipperName": "TUNTQALBjfoWUFhUesxKUqHFglacdzTk",
        "ProductID": 340740506,
        "ProductName": "tXIKDNizIJVlPXlEtYKvMvMYLqKHFhev",
        "UnitPrice": 1963155460.5439,
        "Quantity": 19141,
        "Discount": 56.123,
        "ExtendedPrice": 84951714472.8451,
        "Freight": 41840042592.9576
    },
    {
        "ShipName": "ShipName26",
        "ShipAddress": "ShipAddress26",
        "ShipCity": "ShipCity26",
        "ShipRegion": "ShipRegion26",
        "ShipPostalCode": "ShipPost26",
        "ShipCountry": "ShipCountry26",
        "CustomerID": "Cus26",
        "CustomerName": "UrMJrbsEuObiEHJcfBnfOllJUaLESOWo",
        "Address": "Address26",
        "City": "City26",
        "Region": "Region26",
        "PostalCode": "PostalCo26",
        "Country": "Country26",
        "Salesperson": "vFwzqtjFxjBcKbAWVKQjKqCcFjorDaJ",
        "OrderID": 177536822,
        "OrderDate": "/Date(523335245000)/",
        "RequiredDate": "/Date(692431538000)/",
        "ShippedDate": "/Date(158783156000)/",
        "ShipperName": "PTKdfJlGzKQnfnhOTMkqwtlymJzUZztf",
        "ProductID": 1438999224,
        "ProductName": "nkZQwYHWaSHuhnIpeUCVsGNCWcaWWFTW",
        "UnitPrice": 23489243676.8859,
        "Quantity": 2194,
        "Discount": 9.286,
        "ExtendedPrice": 53453210322.1863,
        "Freight": 22941610263.6605
    },
    {
        "ShipName": "ShipName27",
        "ShipAddress": "ShipAddress27",
        "ShipCity": "ShipCity27",
        "ShipRegion": "ShipRegion27",
        "ShipPostalCode": "ShipPost27",
        "ShipCountry": "ShipCountry27",
        "CustomerID": "Cus27",
        "CustomerName": "PkgkPSgwsMEknAflYnhAORRYgIEeTlKn",
        "Address": "Address27",
        "City": "City27",
        "Region": "Region27",
        "PostalCode": "PostalCo27",
        "Country": "Country27",
        "Salesperson": "SOnmgkupwjYOfhcHfUTDBWmpPZggffm",
        "OrderID": 1959368837,
        "OrderDate": "/Date(334785979000)/",
        "RequiredDate": "/Date(421690691000)/",
        "ShippedDate": "/Date(1185279876000)/",
        "ShipperName": "yXPQjDctUVxIogxlJXUmDNssbramrtWM",
        "ProductID": 1874977686,
        "ProductName": "hWmyKoKMPRgfhlbEXxHuGDgONtxqZlgg",
        "UnitPrice": 27131469291.6348,
        "Quantity": 13571,
        "Discount": 45.703,
        "ExtendedPrice": 30152154783.7182,
        "Freight": 2382053970.3592
    },
    {
        "ShipName": "ShipName28",
        "ShipAddress": "ShipAddress28",
        "ShipCity": "ShipCity28",
        "ShipRegion": "ShipRegion28",
        "ShipPostalCode": "ShipPost28",
        "ShipCountry": "ShipCountry28",
        "CustomerID": "Cus28",
        "CustomerName": "IVtMzYdJthKxMaonEYfoZMqwILXFTZQp",
        "Address": "Address28",
        "City": "City28",
        "Region": "Region28",
        "PostalCode": "PostalCo28",
        "Country": "Country28",
        "Salesperson": "ZCoKMVXojIpBBsvohiXixmIbYdDNXvB",
        "OrderID": 530187736,
        "OrderDate": "/Date(1377440629000)/",
        "RequiredDate": "/Date(1330126535000)/",
        "ShippedDate": "/Date(1193534602000)/",
        "ShipperName": "EzvdwSzkGoZnrpPIBYYbxnPIjSEUbyGw",
        "ProductID": 2023163414,
        "ProductName": "KkJWIJBjLVOennsEDCYFomaDyUnCjTGg",
        "UnitPrice": 1793234306.3876,
        "Quantity": 27797,
        "Discount": 35.355,
        "ExtendedPrice": 7218817877.5832,
        "Freight": 36205731891.0956
    },
    {
        "ShipName": "ShipName29",
        "ShipAddress": "ShipAddress29",
        "ShipCity": "ShipCity29",
        "ShipRegion": "ShipRegion29",
        "ShipPostalCode": "ShipPost29",
        "ShipCountry": "ShipCountry29",
        "CustomerID": "Cus29",
        "CustomerName": "AmrRxarJnEegLwnMiSSvocsfhuhPQuLZ",
        "Address": "Address29",
        "City": "City29",
        "Region": "Region29",
        "PostalCode": "PostalCo29",
        "Country": "Country29",
        "Salesperson": "GSxQFERPheMbXmawAKxlKXcyIDScRoV",
        "OrderID": 979814765,
        "OrderDate": "/Date(580418407000)/",
        "RequiredDate": "/Date(234851724000)/",
        "ShippedDate": "/Date(426580613000)/",
        "ShipperName": "fQfskfQvsQhCtEoTAjVyZVZZTXidFJFW",
        "ProductID": 2072964762,
        "ProductName": "FAxVqGbcpttZLySIyOkhaMaNTgCIUCQB",
        "UnitPrice": 90334382420.4057,
        "Quantity": 32252,
        "Discount": 5.551,
        "ExtendedPrice": 41646234528.1615,
        "Freight": 77493875101.2086
    },
    {
        "ShipName": "ShipName30",
        "ShipAddress": "ShipAddress30",
        "ShipCity": "ShipCity30",
        "ShipRegion": "ShipRegion30",
        "ShipPostalCode": "ShipPost30",
        "ShipCountry": "ShipCountry30",
        "CustomerID": "Cus30",
        "CustomerName": "kIMIVQBCAWBbThNjCBHjKnodBRaOLRCB",
        "Address": "Address30",
        "City": "City30",
        "Region": "Region30",
        "PostalCode": "PostalCo30",
        "Country": "Country30",
        "Salesperson": "WxYeflguXSYLfWespRmGamrhHECMdrU",
        "OrderID": 176263601,
        "OrderDate": "/Date(175598688000)/",
        "RequiredDate": "/Date(485909198000)/",
        "ShippedDate": "/Date(956885065000)/",
        "ShipperName": "DDyBDJydEajRYjvtCOUVkniOTzLoxFyS",
        "ProductID": 659191467,
        "ProductName": "HxAFlgdbUXRhpSwIzUsFsPxQhqpLdgKF",
        "UnitPrice": 81236667232.5879,
        "Quantity": 5402,
        "Discount": 86.427,
        "ExtendedPrice": 54690251895.2265,
        "Freight": 79060980444.774
    },
    {
        "ShipName": "ShipName31",
        "ShipAddress": "ShipAddress31",
        "ShipCity": "ShipCity31",
        "ShipRegion": "ShipRegion31",
        "ShipPostalCode": "ShipPost31",
        "ShipCountry": "ShipCountry31",
        "CustomerID": "Cus31",
        "CustomerName": "mTvBWPxwfrdhKkVnxRvHhGsEPgYoVUJK",
        "Address": "Address31",
        "City": "City31",
        "Region": "Region31",
        "PostalCode": "PostalCo31",
        "Country": "Country31",
        "Salesperson": "RHHTLWUAYhiKSGmQjXGQeqobnLCHVtu",
        "OrderID": 969770810,
        "OrderDate": "/Date(1457181414000)/",
        "RequiredDate": "/Date(833236874000)/",
        "ShippedDate": "/Date(1077110360000)/",
        "ShipperName": "VCaKghDFxWtmxyRbzjigABiGgxmbJxdH",
        "ProductID": 1184898240,
        "ProductName": "mLIQXYvNLLOTigKkMVoJDaLIJPkvqeJn",
        "UnitPrice": 48657473665.6621,
        "Quantity": 12237,
        "Discount": 89.762,
        "ExtendedPrice": 71715376060.456,
        "Freight": 42947815172.3742
    },
    {
        "ShipName": "ShipName32",
        "ShipAddress": "ShipAddress32",
        "ShipCity": "ShipCity32",
        "ShipRegion": "ShipRegion32",
        "ShipPostalCode": "ShipPost32",
        "ShipCountry": "ShipCountry32",
        "CustomerID": "Cus32",
        "CustomerName": "tcDhfwUBcbcUVrELRZoJySGgTPEfNMgA",
        "Address": "Address32",
        "City": "City32",
        "Region": "Region32",
        "PostalCode": "PostalCo32",
        "Country": "Country32",
        "Salesperson": "dkdBmBlayTXgXpPhEQiqPmnVpSQUMIY",
        "OrderID": 2036986620,
        "OrderDate": "/Date(632339620000)/",
        "RequiredDate": "/Date(518929918000)/",
        "ShippedDate": "/Date(772749612000)/",
        "ShipperName": "YgqglSdYoahSJRRFxnIGPeEFhXsnncgy",
        "ProductID": 1853956144,
        "ProductName": "lLcNyMvonqTCUzHbCWSGqXpfdUkUSCZb",
        "UnitPrice": 746479444.2057,
        "Quantity": 32745,
        "Discount": 39.997,
        "ExtendedPrice": 80461683333.8513,
        "Freight": 70453346497.3792
    },
    {
        "ShipName": "ShipName33",
        "ShipAddress": "ShipAddress33",
        "ShipCity": "ShipCity33",
        "ShipRegion": "ShipRegion33",
        "ShipPostalCode": "ShipPost33",
        "ShipCountry": "ShipCountry33",
        "CustomerID": "Cus33",
        "CustomerName": "tnglDWMpENavRRyyxLGKeDhfmSMJBcRt",
        "Address": "Address33",
        "City": "City33",
        "Region": "Region33",
        "PostalCode": "PostalCo33",
        "Country": "Country33",
        "Salesperson": "JwUWYGTGaPZMwQsjoLvBZJOwZlYQQok",
        "OrderID": 1271896604,
        "OrderDate": "/Date(659505921000)/",
        "RequiredDate": "/Date(1131735937000)/",
        "ShippedDate": "/Date(26462405000)/",
        "ShipperName": "WhSTlacuRKkGaquRnhDgebmPnAmMYyfn",
        "ProductID": 317868320,
        "ProductName": "cNzNcfwDXeynCBvBsYLlBKHHEniRcpQn",
        "UnitPrice": 73309295391.6639,
        "Quantity": 26942,
        "Discount": 49.147,
        "ExtendedPrice": 59879972529.5975,
        "Freight": 19526639417.7451
    },
    {
        "ShipName": "ShipName34",
        "ShipAddress": "ShipAddress34",
        "ShipCity": "ShipCity34",
        "ShipRegion": "ShipRegion34",
        "ShipPostalCode": "ShipPost34",
        "ShipCountry": "ShipCountry34",
        "CustomerID": "Cus34",
        "CustomerName": "EmmnRegbgtgBKLPxUabAwmQKDZSVitQv",
        "Address": "Address34",
        "City": "City34",
        "Region": "Region34",
        "PostalCode": "PostalCo34",
        "Country": "Country34",
        "Salesperson": "RMOVvTOcMRrLKrHbtaHLUKFmSUijbig",
        "OrderID": 1819071858,
        "OrderDate": "/Date(1307966190000)/",
        "RequiredDate": "/Date(28428122000)/",
        "ShippedDate": "/Date(411586700000)/",
        "ShipperName": "eIJiydxkhPXanlbyQjTRIxcIAQvhDZqn",
        "ProductID": 1740543833,
        "ProductName": "STBNfnVLvMJYooVZezkVAyWMmYYbpHBX",
        "UnitPrice": 188746070.4892,
        "Quantity": 29779,
        "Discount": 53.316,
        "ExtendedPrice": 19346539024.2636,
        "Freight": 88328923215.1582
    },
    {
        "ShipName": "ShipName35",
        "ShipAddress": "ShipAddress35",
        "ShipCity": "ShipCity35",
        "ShipRegion": "ShipRegion35",
        "ShipPostalCode": "ShipPost35",
        "ShipCountry": "ShipCountry35",
        "CustomerID": "Cus35",
        "CustomerName": "PKdMKeoLGBlUloIflKnKlnIwfsPjhWqa",
        "Address": "Address35",
        "City": "City35",
        "Region": "Region35",
        "PostalCode": "PostalCo35",
        "Country": "Country35",
        "Salesperson": "VsXagJYkmYXpTexoNHoSLCLeUxOWRag",
        "OrderID": 2019338838,
        "OrderDate": "/Date(227708425000)/",
        "RequiredDate": "/Date(322311595000)/",
        "ShippedDate": "/Date(670066783000)/",
        "ShipperName": "akATPTocVfwvESvypMhdofKFbfqrtNnF",
        "ProductID": 914774870,
        "ProductName": "iCANbAbduVAYDkWqqKFhwoIcITHnobwL",
        "UnitPrice": 17928407946.6015,
        "Quantity": 16298,
        "Discount": 6.681,
        "ExtendedPrice": 52808168833.144,
        "Freight": 98017620015.8894
    },
    {
        "ShipName": "ShipName36",
        "ShipAddress": "ShipAddress36",
        "ShipCity": "ShipCity36",
        "ShipRegion": "ShipRegion36",
        "ShipPostalCode": "ShipPost36",
        "ShipCountry": "ShipCountry36",
        "CustomerID": "Cus36",
        "CustomerName": "DNxohqTfortBMifcXcxrfseSxFvQkiba",
        "Address": "Address36",
        "City": "City36",
        "Region": "Region36",
        "PostalCode": "PostalCo36",
        "Country": "Country36",
        "Salesperson": "SwOAPABaKgvBlAKpoyYxukDccOtHfjw",
        "OrderID": 194063555,
        "OrderDate": "/Date(826896744000)/",
        "RequiredDate": "/Date(1370664396000)/",
        "ShippedDate": "/Date(424735003000)/",
        "ShipperName": "pOMhaeWtTUzzuRLEjrWCOCSxSQgjwCgx",
        "ProductID": 457646117,
        "ProductName": "DxFVrhaliQkIAbDQgFVPdqIwKLIjPrUh",
        "UnitPrice": 35345163824.968,
        "Quantity": 11940,
        "Discount": 93.124,
        "ExtendedPrice": 49490908649.75,
        "Freight": 67274434957.6532
    },
    {
        "ShipName": "ShipName37",
        "ShipAddress": "ShipAddress37",
        "ShipCity": "ShipCity37",
        "ShipRegion": "ShipRegion37",
        "ShipPostalCode": "ShipPost37",
        "ShipCountry": "ShipCountry37",
        "CustomerID": "Cus37",
        "CustomerName": "sMPJGklNduGeVLeQTTpEtgdJxiJcRAPl",
        "Address": "Address37",
        "City": "City37",
        "Region": "Region37",
        "PostalCode": "PostalCo37",
        "Country": "Country37",
        "Salesperson": "AguseBySdzDdKklCZaXRuLPvzUqbdZN",
        "OrderID": 1421305605,
        "OrderDate": "/Date(605017541000)/",
        "RequiredDate": "/Date(1004432037000)/",
        "ShippedDate": "/Date(737211490000)/",
        "ShipperName": "PZNeOvuQiadXafASSynYwyMNupyBscDP",
        "ProductID": 2039454869,
        "ProductName": "IRLyYzrXIoiSorTVUcpqxHWOiTkntJqI",
        "UnitPrice": 30728982528.6716,
        "Quantity": 26290,
        "Discount": 36.682,
        "ExtendedPrice": 44491035072.1329,
        "Freight": 35620530019.5142
    },
    {
        "ShipName": "ShipName38",
        "ShipAddress": "ShipAddress38",
        "ShipCity": "ShipCity38",
        "ShipRegion": "ShipRegion38",
        "ShipPostalCode": "ShipPost38",
        "ShipCountry": "ShipCountry38",
        "CustomerID": "Cus38",
        "CustomerName": "ItzSUvKBJVwTsWlrPETyNlVywUzytZoi",
        "Address": "Address38",
        "City": "City38",
        "Region": "Region38",
        "PostalCode": "PostalCo38",
        "Country": "Country38",
        "Salesperson": "PICYcMILDAMGzhxIVqFDnDWhHsnFnIm",
        "OrderID": 1618926292,
        "OrderDate": "/Date(143599415000)/",
        "RequiredDate": "/Date(39920860000)/",
        "ShippedDate": "/Date(858266585000)/",
        "ShipperName": "JLrojmOcRJaurIbPPVWbSLXnhSRnNHFN",
        "ProductID": 1226995000,
        "ProductName": "oJaXyIxyTpUsSThpaaKVoxrzfEjNrOQV",
        "UnitPrice": 60568085522.3909,
        "Quantity": 30373,
        "Discount": 32.158,
        "ExtendedPrice": 58879841724.4106,
        "Freight": 99217222211.8824
    },
    {
        "ShipName": "ShipName39",
        "ShipAddress": "ShipAddress39",
        "ShipCity": "ShipCity39",
        "ShipRegion": "ShipRegion39",
        "ShipPostalCode": "ShipPost39",
        "ShipCountry": "ShipCountry39",
        "CustomerID": "Cus39",
        "CustomerName": "pMKHNjnIhAkigTHokssDarqUGoWqabkU",
        "Address": "Address39",
        "City": "City39",
        "Region": "Region39",
        "PostalCode": "PostalCo39",
        "Country": "Country39",
        "Salesperson": "fBvmPySwggHGImOHDtaQmzJTzxpiDYL",
        "OrderID": 1511644554,
        "OrderDate": "/Date(1309372895000)/",
        "RequiredDate": "/Date(1232456271000)/",
        "ShippedDate": "/Date(686608010000)/",
        "ShipperName": "qbwrQHuGdYWZJmPdLwgKFHnutIRhGxic",
        "ProductID": 615494861,
        "ProductName": "VdynlLNVliSLcjsnwkbVoFfJDgGsltuC",
        "UnitPrice": 79267934244.126,
        "Quantity": 16729,
        "Discount": 94.846,
        "ExtendedPrice": 34129446465.522,
        "Freight": 76954007777.3854
    },
    {
        "ShipName": "ShipName40",
        "ShipAddress": "ShipAddress40",
        "ShipCity": "ShipCity40",
        "ShipRegion": "ShipRegion40",
        "ShipPostalCode": "ShipPost40",
        "ShipCountry": "ShipCountry40",
        "CustomerID": "Cus40",
        "CustomerName": "wkCbTWYcbQvjYHrMYFHbYGvAgLHmNvuM",
        "Address": "Address40",
        "City": "City40",
        "Region": "Region40",
        "PostalCode": "PostalCo40",
        "Country": "Country40",
        "Salesperson": "qPCMaqrZWJdrXFTXSXhHEUGLSCrxNxc",
        "OrderID": 724468267,
        "OrderDate": "/Date(91453755000)/",
        "RequiredDate": "/Date(345055614000)/",
        "ShippedDate": "/Date(814089353000)/",
        "ShipperName": "TlkRLzMYQwIwukTTPBBWgKAvHCqpTGls",
        "ProductID": 1850721852,
        "ProductName": "gXuRUVgehhflZkMQSZojtTilEebDhKXU",
        "UnitPrice": 51345436414.7037,
        "Quantity": 30573,
        "Discount": 96.788,
        "ExtendedPrice": 56468392512.761,
        "Freight": 64780095475.7258
    }
]