[
    {
        "ShippedDate": "/Date(1456204082000)/",
        "OrderID": 1157960597,
        "Subtotal": 25705183041.2819
    },
    {
        "ShippedDate": "/Date(506860706000)/",
        "OrderID": 2073116599,
        "Subtotal": 83278903574.6827
    },
    {
        "ShippedDate": "/Date(294432536000)/",
        "OrderID": 1969161943,
        "Subtotal": 47877893340.7738
    },
    {
        "ShippedDate": "/Date(60504095000)/",
        "OrderID": 786096633,
        "Subtotal": 33257400547.1542
    },
    {
        "ShippedDate": "/Date(220600502000)/",
        "OrderID": 1881489308,
        "Subtotal": 92783937230.7062
    },
    {
        "ShippedDate": "/Date(432861096000)/",
        "OrderID": 1883703413,
        "Subtotal": 34005862358.0262
    },
    {
        "ShippedDate": "/Date(326325108000)/",
        "OrderID": 1541385807,
        "Subtotal": 84473393531.5161
    },
    {
        "ShippedDate": "/Date(575580211000)/",
        "OrderID": 1980016038,
        "Subtotal": 81233844486.9965
    },
    {
        "ShippedDate": "/Date(1311886590000)/",
        "OrderID": 445759756,
        "Subtotal": 41346641979.1802
    },
    {
        "ShippedDate": "/Date(1105059376000)/",
        "OrderID": 1912274358,
        "Subtotal": 24039269774.2208
    },
    {
        "ShippedDate": "/Date(1372724196000)/",
        "OrderID": 1166531261,
        "Subtotal": 38993617915.5483
    },
    {
        "ShippedDate": "/Date(48253431000)/",
        "OrderID": 811644093,
        "Subtotal": 94489418598.8232
    },
    {
        "ShippedDate": "/Date(1293275500000)/",
        "OrderID": 1630636598,
        "Subtotal": 13224246539.1755
    },
    {
        "ShippedDate": "/Date(132301315000)/",
        "OrderID": 1565904163,
        "Subtotal": 39382366277.2774
    },
    {
        "ShippedDate": "/Date(705883850000)/",
        "OrderID": 262804157,
        "Subtotal": 65803543827.4964
    },
    {
        "ShippedDate": "/Date(888405944000)/",
        "OrderID": 1327491133,
        "Subtotal": 33042634488.0834
    },
    {
        "ShippedDate": "/Date(824369215000)/",
        "OrderID": 1173246710,
        "Subtotal": 80258074845.1873
    },
    {
        "ShippedDate": "/Date(76168304000)/",
        "OrderID": 1286061617,
        "Subtotal": 25466733612.1201
    },
    {
        "ShippedDate": "/Date(1412890958000)/",
        "OrderID": 345461523,
        "Subtotal": 56815553992.0553
    },
    {
        "ShippedDate": "/Date(1233095543000)/",
        "OrderID": 1423456469,
        "Subtotal": 12533101742.1558
    },
    {
        "ShippedDate": "/Date(692238009000)/",
        "OrderID": 929078814,
        "Subtotal": 37929457984.8647
    },
    {
        "ShippedDate": "/Date(1439811911000)/",
        "OrderID": 3177657,
        "Subtotal": 31058343616.3142
    },
    {
        "ShippedDate": "/Date(920697183000)/",
        "OrderID": 932305323,
        "Subtotal": 74866537656.635
    },
    {
        "ShippedDate": "/Date(989907943000)/",
        "OrderID": 1273399652,
        "Subtotal": 21596835344.0985
    },
    {
        "ShippedDate": "/Date(141001293000)/",
        "OrderID": 1622770271,
        "Subtotal": 2155381231.5687
    },
    {
        "ShippedDate": "/Date(71969157000)/",
        "OrderID": 1340972043,
        "Subtotal": 66404737415.7235
    },
    {
        "ShippedDate": "/Date(281016958000)/",
        "OrderID": 538909338,
        "Subtotal": 32319324021.2276
    },
    {
        "ShippedDate": "/Date(803685442000)/",
        "OrderID": 1846485885,
        "Subtotal": 17592598102.0554
    },
    {
        "ShippedDate": "/Date(1132229942000)/",
        "OrderID": 1822360217,
        "Subtotal": 64041686197.7428
    },
    {
        "ShippedDate": "/Date(637969690000)/",
        "OrderID": 1396195582,
        "Subtotal": 58937078248.7094
    },
    {
        "ShippedDate": "/Date(1225013068000)/",
        "OrderID": 968126578,
        "Subtotal": 76724378368.8172
    },
    {
        "ShippedDate": "/Date(1296707222000)/",
        "OrderID": 1119873089,
        "Subtotal": 84743251372.1287
    },
    {
        "ShippedDate": "/Date(32367421000)/",
        "OrderID": 472728607,
        "Subtotal": 62255023443.14
    },
    {
        "ShippedDate": "/Date(308392328000)/",
        "OrderID": 1850546407,
        "Subtotal": 75081683322.7872
    },
    {
        "ShippedDate": "/Date(408231289000)/",
        "OrderID": 1594545420,
        "Subtotal": 15649168845.2661
    },
    {
        "ShippedDate": "/Date(851529336000)/",
        "OrderID": 537692991,
        "Subtotal": 65367999696.1727
    },
    {
        "ShippedDate": "/Date(512267690000)/",
        "OrderID": 1114164140,
        "Subtotal": 80994286295.0265
    },
    {
        "ShippedDate": "/Date(672640488000)/",
        "OrderID": 749108736,
        "Subtotal": 59403669298.6264
    },
    {
        "ShippedDate": "/Date(778077711000)/",
        "OrderID": 1372906701,
        "Subtotal": 23960688454.0989
    },
    {
        "ShippedDate": "/Date(1314374104000)/",
        "OrderID": 1389005630,
        "Subtotal": 64040678809.3969
    }
]